tests/__init__.py
tests/test_from_file.py
xmlparser/__init__.py
xmlparser/xmlparser.py
py_xmlparser-1.0.1.dist-info/LICENSE
py_xmlparser-1.0.1.dist-info/METADATA
py_xmlparser-1.0.1.dist-info/WHEEL
py_xmlparser-1.0.1.dist-info/top_level.txt
py_xmlparser-1.0.1.dist-info/RECORD
