Metadata-Version: 2.1
Name: py-xmlparser
Version: 1.0.1
Summary: A python package for parsing xml files into data structures.
Home-page: https://github.com/shachar-oren/xmlparser
Author: Shachar Oren
Author-email: shr.or91@gmail.com
License: UNKNOWN
Platform: UNKNOWN
Classifier: Programming Language :: Python :: 3
Classifier: License :: OSI Approved :: MIT License
Classifier: Operating System :: OS Independent
Requires-Python: >=3.6
